hsc_assembler/__init__.py
hsc_assembler/__main__.py
hsc_assembler/asm_parser.py
hsc_assembler/main.py
hsc_assembler/scanner.py
hsc_assembler/token_enums.py
hsc_assembler-0.3.0.dist-info/entry_points.txt
hsc_assembler-0.3.0.dist-info/WHEEL
hsc_assembler-0.3.0.dist-info/METADATA
hsc_assembler-0.3.0.dist-info/RECORD
